pynotifyd/__init__.py
pynotifyd/lel.py
pynotifyd/main.py
pynotifyd-0.0.2.data/scripts/main.py
pynotifyd-0.0.2.data/scripts/pynotifyd
pynotifyd-0.0.2.dist-info/METADATA
pynotifyd-0.0.2.dist-info/RECORD
pynotifyd-0.0.2.dist-info/WHEEL
pynotifyd-0.0.2.dist-info/top_level.txt
