Metadata-Version: 2.1
Name: pynotifyd
Version: 0.0.2
Summary: Simple notification server
Home-page: https://github.com/ricede/pynotifyd
Author: Tudor Roman
Author-email: tudurom@gmail.com
License: UNKNOWN
Platform: UNKNOWN
Classifier: Programming Language :: Python :: 3
Classifier: License :: OSI Approved :: ISC License (ISCL)
Classifier: Operating System :: POSIX
Classifier: Topic :: Desktop Environment
Requires-Python: >=3.5
Requires-Dist: PyGObject
Requires-Dist: dbus-python
